[
{"text_ru":"Жанна Фриске и Джиган \u2014 Ты Рядом \u2014 Скачать песню...","created_at":"2015-09-20T18:22:32Z","id":"645724750967386112","lang":"ru","tweet_url":[],"tweet_hashtags":[],"favorited":"false","retweeted":"false"},
{"text_ru":"RT @VeraGolovacheva: Мне нравится,как музыка может переносить тебя в разные места. Например,сейчас в этом кафе играет Джиган,и мы уже едем \u2026","created_at":"2015-09-20T18:08:05Z","id":"645721117127274496","lang":"ru","tweet_url":[],"tweet_hashtags":[],"favorited":"false","retweeted":"false"},
{"text_ru":"@ImmaBumbleBeezy @BigRussianBaws ты плачущий Джиган.","created_at":"2015-09-20T17:51:39Z","id":"645716981572726784","lang":"ru","tweet_url":[],"tweet_hashtags":[],"favorited":"false","retweeted":"false"},
{"text_ru":"Устроим аухимительную тусу сказал джиган. Да, Джиган именно такую","created_at":"2015-09-20T17:34:42Z","id":"645712713130209280","lang":"ru","tweet_url":[],"tweet_hashtags":[],"favorited":"false","retweeted":"false"},
{"text_ru":"Джиган поет для счастливый мокрой толстушки","created_at":"2015-09-20T17:30:50Z","id":"645711741767122944","lang":"ru","tweet_url":[],"tweet_hashtags":[],"favorited":"false","retweeted":"false"},
{"text_ru":"RT @atykhonravova: Мне нравится,как музыка может переносить тебя в разные места. Например,сейчас в этом кафе играет Джиган,и мы уже едем в \u2026","created_at":"2015-09-20T17:27:07Z","id":"645710807691476992","lang":"ru","tweet_url":[],"tweet_hashtags":[],"favorited":"false","retweeted":"false"},
{"text_ru":"Джиган - Ахумилительная туса https://t.co/82l1oIZK88","created_at":"2015-09-20T17:21:08Z","id":"645709302099918848","lang":"ru","tweet_url":["https://youtu.be/KMFAySvkgcs"],"tweet_hashtags":[],"favorited":"false","retweeted":"false"},
{"text_ru":"RT @VeraGolovacheva: Мне нравится,как музыка может переносить тебя в разные места. Например,сейчас в этом кафе играет Джиган,и мы уже едем \u2026","created_at":"2015-09-20T16:59:16Z","id":"645703798422241281","lang":"ru","tweet_url":[],"tweet_hashtags":[],"favorited":"false","retweeted":"false"},
{"text_ru":"RT @VeraGolovacheva: Мне нравится,как музыка может переносить тебя в разные места. Например,сейчас в этом кафе играет Джиган,и мы уже едем \u2026","created_at":"2015-09-20T16:56:24Z","id":"645703075940839424","lang":"ru","tweet_url":[],"tweet_hashtags":[],"favorited":"false","retweeted":"false"},
{"text_ru":"RT @humortwi: Мне нравится, как музыка может переносить тебя в разные места. Например, сейчас в этом кафе играет Джиган, и мы уже едем в др\u2026","created_at":"2015-09-20T16:53:11Z","id":"645702265257357313","lang":"ru","tweet_url":[],"tweet_hashtags":[],"favorited":"false","retweeted":"false"},
{"text_ru":"Мне нравится,как музыка может переносить тебя в разные места. Например,сейчас в этом кафе играет Джиган,и мы уже едем в другое кафе","created_at":"2015-09-20T15:58:39Z","id":"645688543763894272","lang":"ru","tweet_url":[],"tweet_hashtags":[],"favorited":"false","retweeted":"false"},
{"text_ru":"RT @VeraGolovacheva: Мне нравится,как музыка может переносить тебя в разные места. Например,сейчас в этом кафе играет Джиган,и мы уже едем \u2026","created_at":"2015-09-20T15:19:29Z","id":"645678684897157120","lang":"ru","tweet_url":[],"tweet_hashtags":[],"favorited":"false","retweeted":"false"},
{"text_ru":"RT @VeraGolovacheva: Мне нравится,как музыка может переносить тебя в разные места. Например,сейчас в этом кафе играет Джиган,и мы уже едем \u2026","created_at":"2015-09-20T15:11:44Z","id":"645676734403190785","lang":"ru","tweet_url":[],"tweet_hashtags":[],"favorited":"false","retweeted":"false"},
{"text_ru":"мне нравится, как музыка может переносить тебя в разные места. вот, например, сейчас в этом кафе играет Джиган, и мы уже едем в другое кафе.","created_at":"2015-09-20T15:10:48Z","id":"645676499211808768","lang":"ru","tweet_url":[],"tweet_hashtags":[],"favorited":"false","retweeted":"false"},
{"text_ru":"Джиган катает по городу😃\nРили Джиган, зовут его так😑👌\nСкорость😍🙈","created_at":"2015-09-20T15:04:06Z","id":"645674812719923200","lang":"ru","tweet_url":[],"tweet_hashtags":[],"favorited":"false","retweeted":"false"},
{"text_ru":"И да, сегодня к нам приезжал сам великий и ужасный Джиган","created_at":"2015-09-20T14:20:34Z","id":"645663857491505152","lang":"ru","tweet_url":[],"tweet_hashtags":[],"favorited":"false","retweeted":"false"},
{"text_ru":"Мне нравится, как музыка может переносить тебя в другие места. \nНапример, сейчас в этом кафе играет Джиган и мы уже едем в другое кафе.","created_at":"2015-09-20T13:29:32Z","id":"645651015820288000","lang":"ru","tweet_url":[],"tweet_hashtags":[],"favorited":"false","retweeted":"false"},
{"text_ru":"RT @humortwi: Мне нравится, как музыка может переносить тебя в разные места. Например, сейчас в этом кафе играет Джиган, и мы уже едем в др\u2026","created_at":"2015-09-20T13:22:10Z","id":"645649162806165505","lang":"ru","tweet_url":[],"tweet_hashtags":[],"favorited":"false","retweeted":"false"},
{"text_ru":"RT @VeraGolovacheva: Мне нравится,как музыка может переносить тебя в разные места. Например,сейчас в этом кафе играет Джиган,и мы уже едем \u2026","created_at":"2015-09-20T12:56:24Z","id":"645642678407827456","lang":"ru","tweet_url":[],"tweet_hashtags":[],"favorited":"false","retweeted":"false"},
{"text_ru":"Лучший хип-хоп проект - Джиган😃\nНАДО ПОДКАЧАТЬСЯ , НАДО НАДО ПОДКАЧАТЬСЯ💪💪","created_at":"2015-09-20T12:26:19Z","id":"645635108318408705","lang":"ru","tweet_url":[],"tweet_hashtags":[],"favorited":"false","retweeted":"false"},
{"text_ru":"RT @humortwi: Мне нравится, как музыка может переносить тебя в разные места. Например, сейчас в этом кафе играет Джиган, и мы уже едем в др\u2026","created_at":"2015-09-20T12:24:34Z","id":"645634668470140928","lang":"ru","tweet_url":[],"tweet_hashtags":[],"favorited":"false","retweeted":"false"},
{"text_ru":"RT @humortwi: Мне нравится, как музыка может переносить тебя в разные места. Например, сейчас в этом кафе играет Джиган, и мы уже едем в др\u2026","created_at":"2015-09-20T11:12:05Z","id":"645616423859941376","lang":"ru","tweet_url":[],"tweet_hashtags":[],"favorited":"false","retweeted":"false"},
{"text_ru":"Ну сначала был бред\nА потом вышел Джиган и еще ктот","created_at":"2015-09-20T09:52:18Z","id":"645596349342347264","lang":"ru","tweet_url":[],"tweet_hashtags":[],"favorited":"false","retweeted":"false"},
{"text_ru":"RT @humortwi: Мне нравится, как музыка может переносить тебя в разные места. Например, сейчас в этом кафе играет Джиган, и мы уже едем в др\u2026","created_at":"2015-09-20T09:50:19Z","id":"645595849792356352","lang":"ru","tweet_url":[],"tweet_hashtags":[],"favorited":"false","retweeted":"false"},
{"text_ru":"RT @humortwi: Мне нравится, как музыка может переносить тебя в разные места. Например, сейчас в этом кафе играет Джиган, и мы уже едем в др\u2026","created_at":"2015-09-20T09:43:08Z","id":"645594042638684160","lang":"ru","tweet_url":[],"tweet_hashtags":[],"favorited":"false","retweeted":"false"},
{"text_ru":"RT @humortwi: Мне нравится, как музыка может переносить тебя в разные места. Например, сейчас в этом кафе играет Джиган, и мы уже едем в др\u2026","created_at":"2015-09-20T09:16:09Z","id":"645587250194026497","lang":"ru","tweet_url":[],"tweet_hashtags":[],"favorited":"false","retweeted":"false"},
{"text_ru":"RT @VeraGolovacheva: Мне нравится,как музыка может переносить тебя в разные места. Например,сейчас в этом кафе играет Джиган,и мы уже едем \u2026","created_at":"2015-09-20T09:11:42Z","id":"645586130579144704","lang":"ru","tweet_url":[],"tweet_hashtags":[],"favorited":"false","retweeted":"false"},
{"text_ru":"RT @humortwi: Мне нравится, как музыка может переносить тебя в разные места. Например, сейчас в этом кафе играет Джиган, и мы уже едем в др\u2026","created_at":"2015-09-20T09:11:15Z","id":"645586017660104704","lang":"ru","tweet_url":[],"tweet_hashtags":[],"favorited":"false","retweeted":"false"},
{"text_ru":"@_k_real_ @GrishkaUrgant @VeraGolovacheva Вот где сворован, но побоялся что увидет Джиган https://t.co/1ZUb1ynVAo","created_at":"2015-09-20T09:08:45Z","id":"645585386987757569","lang":"ru","tweet_url":["https://twitter.com/KapitanKenguru/status/645485156254490624?s=09"],"tweet_hashtags":[],"favorited":"false","retweeted":"false"},
{"text_ru":"RT @humortwi: Мне нравится, как музыка может переносить тебя в разные места. Например, сейчас в этом кафе играет Джиган, и мы уже едем в др\u2026","created_at":"2015-09-20T08:59:06Z","id":"645582959882465280","lang":"ru","tweet_url":[],"tweet_hashtags":[],"favorited":"false","retweeted":"false"},
{"text_ru":"RT @pas_cliche: Мне нравится, как музыка может переносить в другие места. Например, в этом кафе играет Джиган. И вот, мы уже едем в другое \u2026","created_at":"2015-09-20T08:55:45Z","id":"645582116835749888","lang":"ru","tweet_url":[],"tweet_hashtags":[],"favorited":"false","retweeted":"false"},
{"text_ru":"сидела слухала экс а потом в плейлисте резко заиграл джиган\n\nродители зырят","created_at":"2015-09-20T08:52:10Z","id":"645581216515792896","lang":"ru","tweet_url":[],"tweet_hashtags":[],"favorited":"false","retweeted":"false"},
{"text_ru":"RT @VeraGolovacheva: Мне нравится,как музыка может переносить тебя в разные места. Например,сейчас в этом кафе играет Джиган,и мы уже едем \u2026","created_at":"2015-09-20T08:50:22Z","id":"645580762679480320","lang":"ru","tweet_url":[],"tweet_hashtags":[],"favorited":"false","retweeted":"false"},
{"text_ru":"RT @humortwi: Мне нравится, как музыка может переносить тебя в разные места. Например, сейчас в этом кафе играет Джиган, и мы уже едем в др\u2026","created_at":"2015-09-20T08:45:01Z","id":"645579415645237248","lang":"ru","tweet_url":[],"tweet_hashtags":[],"favorited":"false","retweeted":"false"},
{"text_ru":"RT @humortwi: Мне нравится, как музыка может переносить тебя в разные места. Например, сейчас в этом кафе играет Джиган, и мы уже едем в др\u2026","created_at":"2015-09-20T07:52:28Z","id":"645566191319126017","lang":"ru","tweet_url":[],"tweet_hashtags":[],"favorited":"false","retweeted":"false"},
{"text_ru":"RT @humortwi: Мне нравится, как музыка может переносить тебя в разные места. Например, сейчас в этом кафе играет Джиган, и мы уже едем в др\u2026","created_at":"2015-09-20T07:51:59Z","id":"645566070707879937","lang":"ru","tweet_url":[],"tweet_hashtags":[],"favorited":"false","retweeted":"false"},
{"text_ru":"RT @humortwi: Мне нравится, как музыка может переносить тебя в разные места. Например, сейчас в этом кафе играет Джиган, и мы уже едем в др\u2026","created_at":"2015-09-20T07:51:49Z","id":"645566025480560640","lang":"ru","tweet_url":[],"tweet_hashtags":[],"favorited":"false","retweeted":"false"},
{"text_ru":"RT @humortwi: Мне нравится, как музыка может переносить тебя в разные места. Например, сейчас в этом кафе играет Джиган, и мы уже едем в др\u2026","created_at":"2015-09-20T07:45:07Z","id":"645564341136265217","lang":"ru","tweet_url":[],"tweet_hashtags":[],"favorited":"false","retweeted":"false"},
{"text_ru":"RT @humortwi: Мне нравится, как музыка может переносить тебя в разные места. Например, сейчас в этом кафе играет Джиган, и мы уже едем в др\u2026","created_at":"2015-09-20T07:43:56Z","id":"645564043579760640","lang":"ru","tweet_url":[],"tweet_hashtags":[],"favorited":"false","retweeted":"false"},
{"text_ru":"RT @humortwi: Мне нравится, как музыка может переносить тебя в разные места. Например, сейчас в этом кафе играет Джиган, и мы уже едем в др\u2026","created_at":"2015-09-20T07:35:00Z","id":"645561796292669440","lang":"ru","tweet_url":[],"tweet_hashtags":[],"favorited":"false","retweeted":"false"},
{"text_ru":"RT @humortwi: Мне нравится, как музыка может переносить тебя в разные места. Например, сейчас в этом кафе играет Джиган, и мы уже едем в др\u2026","created_at":"2015-09-20T07:19:36Z","id":"645557917501030401","lang":"ru","tweet_url":[],"tweet_hashtags":[],"favorited":"false","retweeted":"false"},
{"text_ru":"Джиган - Твой выбор (Премьера клипа) https://t.co/Eqnh8pXf2M","created_at":"2015-09-20T06:51:17Z","id":"645550793584713728","lang":"ru","tweet_url":["https://youtube.com/watch?v=OgpzdlCS6VU"],"tweet_hashtags":[],"favorited":"false","retweeted":"false"},
{"text_ru":"RT @humortwi: Мне нравится, как музыка может переносить тебя в разные места. Например, сейчас в этом кафе играет Джиган, и мы уже едем в др\u2026","created_at":"2015-09-20T05:44:46Z","id":"645534052943011840","lang":"ru","tweet_url":[],"tweet_hashtags":[],"favorited":"false","retweeted":"false"},
{"text_ru":"RT @humortwi: Мне нравится, как музыка может переносить тебя в разные места. Например, сейчас в этом кафе играет Джиган, и мы уже едем в др\u2026","created_at":"2015-09-20T05:41:37Z","id":"645533261695950849","lang":"ru","tweet_url":[],"tweet_hashtags":[],"favorited":"false","retweeted":"false"},
{"text_ru":"RT @humortwi: Мне нравится, как музыка может переносить тебя в разные места. Например, сейчас в этом кафе играет Джиган, и мы уже едем в др\u2026","created_at":"2015-09-20T05:30:58Z","id":"645530581695074304","lang":"ru","tweet_url":[],"tweet_hashtags":[],"favorited":"false","retweeted":"false"},
{"text_ru":"RT @VeraGolovacheva: Мне нравится,как музыка может переносить тебя в разные места. Например,сейчас в этом кафе играет Джиган,и мы уже едем \u2026","created_at":"2015-09-20T05:26:47Z","id":"645529528962564096","lang":"ru","tweet_url":[],"tweet_hashtags":[],"favorited":"false","retweeted":"false"},
{"text_ru":"RT @Rhymes_News: Мне нравится,как музыка может переносить тебя в разные места.Например,сейчас в этом кафе играет Джиган,и мы уже едем в дру\u2026","created_at":"2015-09-20T05:21:06Z","id":"645528098918764544","lang":"ru","tweet_url":[],"tweet_hashtags":["спизжено"],"favorited":"false","retweeted":"false"},
{"text_ru":"RT @VeraGolovacheva: Мне нравится,как музыка может переносить тебя в разные места. Например,сейчас в этом кафе играет Джиган,и мы уже едем \u2026","created_at":"2015-09-20T04:10:33Z","id":"645510341699444736","lang":"ru","tweet_url":[],"tweet_hashtags":[],"favorited":"false","retweeted":"false"},
{"text_ru":"#взаимно Премьера! Джиган - Надо подкачаться https://t.co/DBISSPeIOA","created_at":"2015-09-20T04:08:27Z","id":"645509816677441537","lang":"ru","tweet_url":["https://youtube.com/watch?v=7lts0mL24kI"],"tweet_hashtags":["взаимно"],"favorited":"false","retweeted":"false"},
{"text_ru":"RT @VeraGolovacheva: Мне нравится,как музыка может переносить тебя в разные места. Например,сейчас в этом кафе играет Джиган,и мы уже едем \u2026","created_at":"2015-09-20T04:03:50Z","id":"645508653362073600","lang":"ru","tweet_url":[],"tweet_hashtags":[],"favorited":"false","retweeted":"false"},
{"text_ru":"Клип Ахумилительная туса - Джиган http://t.co/UOgCkMkBBx","created_at":"2015-09-20T03:28:23Z","id":"645499730034880512","lang":"ru","tweet_url":["http://vk.cc/4dnfUb"],"tweet_hashtags":[],"favorited":"false","retweeted":"false"},
{"text_ru":"джиган и юлия савичева осколки скачать бесплатно","created_at":"2015-09-20T03:15:24Z","id":"645496464190382080","lang":"ru","tweet_url":[],"tweet_hashtags":[],"favorited":"false","retweeted":"false"},
{"text_ru":"RT @VeraGolovacheva: Мне нравится,как музыка может переносить тебя в разные места. Например,сейчас в этом кафе играет Джиган,и мы уже едем \u2026","created_at":"2015-09-20T02:55:01Z","id":"645491336431443968","lang":"ru","tweet_url":[],"tweet_hashtags":[],"favorited":"false","retweeted":"false"},
{"text_ru":"RT @VeraGolovacheva: Мне нравится,как музыка может переносить тебя в разные места. Например,сейчас в этом кафе играет Джиган,и мы уже едем \u2026","created_at":"2015-09-20T01:36:17Z","id":"645471520026951680","lang":"ru","tweet_url":[],"tweet_hashtags":[],"favorited":"false","retweeted":"false"},
{"text_ru":"RT @VeraGolovacheva: Мне нравится,как музыка может переносить тебя в разные места. Например,сейчас в этом кафе играет Джиган,и мы уже едем \u2026","created_at":"2015-09-20T01:15:13Z","id":"645466219294756864","lang":"ru","tweet_url":[],"tweet_hashtags":[],"favorited":"false","retweeted":"false"},
{"text_ru":"RT @humortwi: Мне нравится, как музыка может переносить тебя в разные места. Например, сейчас в этом кафе играет Джиган, и мы уже едем в др\u2026","created_at":"2015-09-20T01:09:35Z","id":"645464803453046784","lang":"ru","tweet_url":[],"tweet_hashtags":[],"favorited":"false","retweeted":"false"},
{"text_ru":"Жанна Фриске и Джиган \u2014 Ты Рядом \u2014 Скачать песню...","created_at":"2015-09-20T01:00:01Z","id":"645462393053683713","lang":"ru","tweet_url":[],"tweet_hashtags":[],"favorited":"false","retweeted":"false"},
{"text_ru":"Жанна Фриске и Джиган \u2014 Ты Рядом \u2014 Скачать песню...","created_at":"2015-09-20T00:59:53Z","id":"645462362326204416","lang":"ru","tweet_url":[],"tweet_hashtags":[],"favorited":"false","retweeted":"false"},
{"text_ru":"Жанна Фриске и Джиган \u2014 Ты Рядом \u2014 Скачать песню...","created_at":"2015-09-20T00:59:49Z","id":"645462342227095552","lang":"ru","tweet_url":[],"tweet_hashtags":[],"favorited":"false","retweeted":"false"},
{"text_ru":"Жанна Фриске и Джиган \u2014 Ты Рядом \u2014 Скачать песню...","created_at":"2015-09-20T00:58:56Z","id":"645462120088346625","lang":"ru","tweet_url":[],"tweet_hashtags":[],"favorited":"false","retweeted":"false"},
{"text_ru":"Жанна Фриске и Джиган \u2014 Ты Рядом \u2014 Скачать песню...","created_at":"2015-09-20T00:58:53Z","id":"645462110273708032","lang":"ru","tweet_url":[],"tweet_hashtags":[],"favorited":"false","retweeted":"false"},
{"text_ru":"Жанна Фриске и Джиган \u2014 Ты Рядом \u2014 Скачать песню...","created_at":"2015-09-20T00:58:53Z","id":"645462109149626369","lang":"ru","tweet_url":[],"tweet_hashtags":[],"favorited":"false","retweeted":"false"},
{"text_ru":"Жанна Фриске и Джиган \u2014 Ты Рядом \u2014 Скачать песню...","created_at":"2015-09-20T00:58:52Z","id":"645462104812687360","lang":"ru","tweet_url":[],"tweet_hashtags":[],"favorited":"false","retweeted":"false"},
{"text_ru":"Жанна Фриске и Джиган \u2014 Ты Рядом \u2014 Скачать песню...","created_at":"2015-09-20T00:58:50Z","id":"645462094788329472","lang":"ru","tweet_url":[],"tweet_hashtags":[],"favorited":"false","retweeted":"false"},
{"text_ru":"Жанна Фриске и Джиган \u2014 Ты Рядом \u2014 Скачать песню...","created_at":"2015-09-20T00:58:10Z","id":"645461927649484800","lang":"ru","tweet_url":[],"tweet_hashtags":[],"favorited":"false","retweeted":"false"},
{"text_ru":"Жанна Фриске и Джиган \u2014 Ты Рядом \u2014 Скачать песню...","created_at":"2015-09-20T00:57:58Z","id":"645461876965527552","lang":"ru","tweet_url":[],"tweet_hashtags":[],"favorited":"false","retweeted":"false"},
{"text_ru":"Жанна Фриске и Джиган \u2014 Ты Рядом \u2014 Скачать песню...","created_at":"2015-09-20T00:57:55Z","id":"645461864554594305","lang":"ru","tweet_url":[],"tweet_hashtags":[],"favorited":"false","retweeted":"false"},
{"text_ru":"Жанна Фриске и Джиган \u2014 Ты Рядом \u2014 Скачать песню...","created_at":"2015-09-20T00:57:54Z","id":"645461861035548672","lang":"ru","tweet_url":[],"tweet_hashtags":[],"favorited":"false","retweeted":"false"},
{"text_ru":"Жанна Фриске и Джиган \u2014 Ты Рядом \u2014 Скачать песню...","created_at":"2015-09-20T00:57:45Z","id":"645461824649981952","lang":"ru","tweet_url":[],"tweet_hashtags":[],"favorited":"false","retweeted":"false"},
{"text_ru":"Жанна Фриске и Джиган \u2014 Ты Рядом \u2014 Скачать песню...","created_at":"2015-09-20T00:57:06Z","id":"645461659256008704","lang":"ru","tweet_url":[],"tweet_hashtags":[],"favorited":"false","retweeted":"false"},
{"text_ru":"Жанна Фриске и Джиган \u2014 Ты Рядом \u2014 Скачать песню...","created_at":"2015-09-20T00:56:53Z","id":"645461603454971904","lang":"ru","tweet_url":[],"tweet_hashtags":[],"favorited":"false","retweeted":"false"},
{"text_ru":"Жанна Фриске и Джиган \u2014 Ты Рядом \u2014 Скачать песню...","created_at":"2015-09-20T00:55:01Z","id":"645461133797814272","lang":"ru","tweet_url":[],"tweet_hashtags":[],"favorited":"false","retweeted":"false"},
{"text_ru":"Жанна Фриске и Джиган \u2014 Ты Рядом \u2014 Скачать песню...","created_at":"2015-09-20T00:54:55Z","id":"645461111983226880","lang":"ru","tweet_url":[],"tweet_hashtags":[],"favorited":"false","retweeted":"false"},
{"text_ru":"Жанна Фриске и Джиган \u2014 Ты Рядом \u2014 Скачать песню...","created_at":"2015-09-20T00:54:52Z","id":"645461096531423232","lang":"ru","tweet_url":[],"tweet_hashtags":[],"favorited":"false","retweeted":"false"},
{"text_ru":"Жанна Фриске и Джиган \u2014 Ты Рядом \u2014 Скачать песню...","created_at":"2015-09-20T00:54:51Z","id":"645461094811701248","lang":"ru","tweet_url":[],"tweet_hashtags":[],"favorited":"false","retweeted":"false"},
{"text_ru":"Жанна Фриске и Джиган \u2014 Ты Рядом \u2014 Скачать песню...","created_at":"2015-09-20T00:54:49Z","id":"645461084221124612","lang":"ru","tweet_url":[],"tweet_hashtags":[],"favorited":"false","retweeted":"false"},
{"text_ru":"Жанна Фриске и Джиган \u2014 Ты Рядом \u2014 Скачать песню...","created_at":"2015-09-20T00:54:46Z","id":"645461073676627968","lang":"ru","tweet_url":[],"tweet_hashtags":[],"favorited":"false","retweeted":"false"},
{"text_ru":"Жанна Фриске и Джиган \u2014 Ты Рядом \u2014 Скачать песню...","created_at":"2015-09-20T00:54:40Z","id":"645461049664249856","lang":"ru","tweet_url":[],"tweet_hashtags":[],"favorited":"false","retweeted":"false"},
{"text_ru":"Жанна Фриске и Джиган \u2014 Ты Рядом \u2014 Скачать песню...","created_at":"2015-09-20T00:54:40Z","id":"645461049387433984","lang":"ru","tweet_url":[],"tweet_hashtags":[],"favorited":"false","retweeted":"false"},
{"text_ru":"Жанна Фриске и Джиган \u2014 Ты Рядом \u2014 Скачать песню...","created_at":"2015-09-20T00:52:59Z","id":"645460622726033409","lang":"ru","tweet_url":[],"tweet_hashtags":[],"favorited":"false","retweeted":"false"},
{"text_ru":"Жанна Фриске и Джиган \u2014 Ты Рядом \u2014 Скачать песню...","created_at":"2015-09-20T00:52:48Z","id":"645460578283180032","lang":"ru","tweet_url":[],"tweet_hashtags":[],"favorited":"false","retweeted":"false"},
{"text_ru":"Жанна Фриске и Джиган \u2014 Ты Рядом \u2014 Скачать песню...","created_at":"2015-09-20T00:52:36Z","id":"645460526995251200","lang":"ru","tweet_url":[],"tweet_hashtags":[],"favorited":"false","retweeted":"false"},
{"text_ru":"Жанна Фриске и Джиган \u2014 Ты Рядом \u2014 Скачать песню...","created_at":"2015-09-20T00:52:00Z","id":"645460375400542209","lang":"ru","tweet_url":[],"tweet_hashtags":[],"favorited":"false","retweeted":"false"},
{"text_ru":"Жанна Фриске и Джиган \u2014 Ты Рядом \u2014 Скачать песню...","created_at":"2015-09-20T00:51:18Z","id":"645460198677696512","lang":"ru","tweet_url":[],"tweet_hashtags":[],"favorited":"false","retweeted":"false"},
{"text_ru":"Жанна Фриске и Джиган \u2014 Ты Рядом \u2014 Скачать песню...","created_at":"2015-09-20T00:50:51Z","id":"645460088434597888","lang":"ru","tweet_url":[],"tweet_hashtags":[],"favorited":"false","retweeted":"false"},
{"text_ru":"Жанна Фриске и Джиган \u2014 Ты Рядом \u2014 Скачать песню...","created_at":"2015-09-20T00:50:06Z","id":"645459898323595264","lang":"ru","tweet_url":[],"tweet_hashtags":[],"favorited":"false","retweeted":"false"},
{"text_ru":"Жанна Фриске и Джиган \u2014 Ты Рядом \u2014 Скачать песню...","created_at":"2015-09-20T00:49:54Z","id":"645459848549806080","lang":"ru","tweet_url":[],"tweet_hashtags":[],"favorited":"false","retweeted":"false"},
{"text_ru":"Жанна Фриске и Джиган \u2014 Ты Рядом \u2014 Скачать песню...","created_at":"2015-09-20T00:49:52Z","id":"645459837883678720","lang":"ru","tweet_url":[],"tweet_hashtags":[],"favorited":"false","retweeted":"false"},
{"text_ru":"Жанна Фриске и Джиган \u2014 Ты Рядом \u2014 Скачать песню...","created_at":"2015-09-20T00:49:04Z","id":"645459638834610176","lang":"ru","tweet_url":[],"tweet_hashtags":[],"favorited":"false","retweeted":"false"},
{"text_ru":"Жанна Фриске и Джиган \u2014 Ты Рядом \u2014 Скачать песню...","created_at":"2015-09-20T00:48:37Z","id":"645459524569186305","lang":"ru","tweet_url":[],"tweet_hashtags":[],"favorited":"false","retweeted":"false"},
{"text_ru":"Жанна Фриске и Джиган \u2014 Ты Рядом \u2014 Скачать песню...","created_at":"2015-09-20T00:48:11Z","id":"645459414409981952","lang":"ru","tweet_url":[],"tweet_hashtags":[],"favorited":"false","retweeted":"false"},
{"text_ru":"Жанна Фриске и Джиган \u2014 Ты Рядом \u2014 Скачать песню...","created_at":"2015-09-20T00:48:09Z","id":"645459407493533696","lang":"ru","tweet_url":[],"tweet_hashtags":[],"favorited":"false","retweeted":"false"},
{"text_ru":"Жанна Фриске и Джиган \u2014 Ты Рядом \u2014 Скачать песню...","created_at":"2015-09-20T00:48:04Z","id":"645459388136882176","lang":"ru","tweet_url":[],"tweet_hashtags":[],"favorited":"false","retweeted":"false"},
{"text_ru":"Жанна Фриске и Джиган \u2014 Ты Рядом \u2014 Скачать песню...","created_at":"2015-09-20T00:47:59Z","id":"645459366557167616","lang":"ru","tweet_url":[],"tweet_hashtags":[],"favorited":"false","retweeted":"false"},
{"text_ru":"Жанна Фриске и Джиган \u2014 Ты Рядом \u2014 Скачать песню...","created_at":"2015-09-20T00:47:38Z","id":"645459278204129281","lang":"ru","tweet_url":[],"tweet_hashtags":[],"favorited":"false","retweeted":"false"},
{"text_ru":"RT @humortwi: Мне нравится, как музыка может переносить тебя в разные места. Например, сейчас в этом кафе играет Джиган, и мы уже едем в др\u2026","created_at":"2015-09-20T00:47:32Z","id":"645459251763245056","lang":"ru","tweet_url":[],"tweet_hashtags":[],"favorited":"false","retweeted":"false"},
{"text_ru":"RT @VeraGolovacheva: Мне нравится,как музыка может переносить тебя в разные места. Например,сейчас в этом кафе играет Джиган,и мы уже едем \u2026","created_at":"2015-09-19T22:43:15Z","id":"645427975119339520","lang":"ru","tweet_url":[],"tweet_hashtags":[],"favorited":"false","retweeted":"false"},
{"text_ru":"Жанна Фриске и Джиган \u2014 Ты Рядом \u2014 Скачать песню...","created_at":"2015-09-19T21:37:02Z","id":"645411309744443392","lang":"ru","tweet_url":[],"tweet_hashtags":[],"favorited":"false","retweeted":"false"},
{"text_ru":"Жанна Фриске и Джиган \u2014 Ты Рядом \u2014 Скачать песню...","created_at":"2015-09-19T21:36:57Z","id":"645411291386019840","lang":"ru","tweet_url":[],"tweet_hashtags":[],"favorited":"false","retweeted":"false"},
{"text_ru":"Я ахуел, просто уебала как королева, хоть сейчас жениться :O\n#GeeGun #Джиган  https://t.co/D3smjfTnD9","created_at":"2015-09-19T21:05:35Z","id":"645403395747090432","lang":"ru","tweet_url":["https://twitter.com/VeraGolovacheva/status/643813901470158849"],"tweet_hashtags":["GeeGun","Джиган"],"favorited":"false","retweeted":"false"}
]
